KolejkaClient-0.1.202310121859-nspkg.pth
kolejka/client/__init__.py
kolejka/client/__nonpath__.py
kolejka/client/client.py
KolejkaClient-0.1.202310121859.dist-info/METADATA
KolejkaClient-0.1.202310121859.dist-info/WHEEL
KolejkaClient-0.1.202310121859.dist-info/entry_points.txt
KolejkaClient-0.1.202310121859.dist-info/namespace_packages.txt
KolejkaClient-0.1.202310121859.dist-info/top_level.txt
KolejkaClient-0.1.202310121859.dist-info/RECORD
