Metadata-Version: 2.1
Name: KolejkaClient
Version: 0.1.202310121859
Summary: Kolejka Client
Home-page: https://github.com/kolejka/kolejka
Author: KOLEJKA
Author-email: kolejka@matinf.uj.edu.pl
License: MIT
Platform: UNKNOWN
Requires-Python: >=3.7
Requires-Dist: KolejkaCommon
Requires-Dist: appdirs
Requires-Dist: requests
Requires-Dist: setproctitle
